{"fields": [{"field_id": 0, "field_name": "VendorName", "key_id": [], "key_text": "", "value_id": [314, 315, 316], "value_text": "NH Hoteles Espa\u00f1a SA", "unit_id": [], "unit_text": "", "status": "ARGUS_original"}, {"field_id": 1, "field_name": "VendorTaxID", "key_id": [318], "key_text": "CIF", "value_id": [318, 319, 320], "value_text": "A - 58511882", "unit_id": [], "unit_text": "", "status": "ARGUS_original"}, {"field_id": 2, "field_name": "InvoiceDate", "key_id": [79], "key_text": "Fecha", "value_id": [80, 81, 82, 83, 84], "value_text": "01 . 06 . 2017", "unit_id": [], "unit_text": "", "status": "ARGUS_original"}, {"field_id": 3, "field_name": "InvoiceNumber", "key_id": [73, 74, 75], "key_text": "Num . Facture", "value_id": [76], "value_text": "4104041644", "unit_id": [], "unit_text": "", "status": "ARGUS_original"}, {"field_id": 4, "field_name": "BaseAmount", "key_id": [278], "key_text": "Base", "value_id": [300, 301, 302], "value_text": "258 . 45", "unit_id": [], "unit_text": "", "status": "ARGUS_original"}, {"field_id": 5, "field_name": "TaxAmount", "key_id": [282], "key_text": "Cuota", "value_id": [303, 304, 305], "value_text": "25 , 85", "unit_id": [], "unit_text": "", "status": "ARGUS_original"}, {"field_id": 6, "field_name": "TaxRate", "key_id": [276], "key_text": "%IVA", "value_id": [286, 287, 288, 289], "value_text": "10 . 00 %", "unit_id": [], "unit_text": "", "status": "ARGUS_original"}, {"field_id": 7, "field_name": "ExpenseAmount", "key_id": [277], "key_text": "Total", "value_id": [295, 296, 297, 299], "value_text": "284 , 30 EUR", "unit_id": [], "unit_text": "", "status": "ARGUS_original"}, {"field_id": 8, "field_name": "InvoiceCompanyCode", "key_id": [], "key_text": "", "value_id": [36, 37], "value_text": "ACCENTURE SL", "unit_id": [], "unit_text": "", "status": "ARGUS_original"}, {"field_id": 9, "field_name": "SIIInvoiceType", "key_id": [], "key_text": "", "value_id": [], "value_text": "", "unit_id": [], "unit_text": "", "status": "ARGUS_original"}, {"field_id": 10, "field_name": "DeductibleOrNot", "key_id": [], "key_text": "", "value_id": [], "value_text": "", "unit_id": [], "unit_text": "", "status": "ARGUS_original"}], "text_boxes": [{"id": 0, "bbox": [[326, 81], [334, 81], [334, 98], [326, 98]], "text": "NH", "confidence": 0.9900000095367432, "status": "ARGUS_original"}, {"id": 1, "bbox": [[348, 81], [364, 81], [364, 98], [348, 98]], "text": "Les", "confidence": 0.9700000286102295, "status": "ARGUS_original"}, {"id": 2, "bbox": [[375, 81], [406, 82], [406, 100], [375, 99]], "text": "Corts", "confidence": 0.9900000095367432, "status": "ARGUS_original"}, {"id": 3, "bbox": [[325, 106], [392, 105], [392, 123], [325, 124]], "text": "TRAVESSERA", "confidence": 0.9900000095367432, "status": "ARGUS_original"}, {"id": 4, "bbox": [[402, 105], [410, 105], [410, 122], [402, 122]], "text": "DE", "confidence": 0.9900000095367432, "status": "ARGUS_original"}, {"id": 5, "bbox": [[421, 105], [440, 105], [440, 122], [421, 122]], "text": "LES", "confidence": 0.9900000095367432, "status": "ARGUS_original"}, {"id": 6, "bbox": [[448, 104], [482, 103], [482, 121], [448, 122]], "text": "CORTS", "confidence": 0.9900000095367432, "status": "ARGUS_original"}, {"id": 7, "bbox": [[492, 104], [509, 104], [509, 121], [492, 121]], "text": "292", "confidence": 0.9900000095367432, "status": "ARGUS_original"}, {"id": 8, "bbox": [[326, 132], [358, 132], [358, 148], [326, 148]], "text": "08029", "confidence": 0.8500000238418579, "status": "ARGUS_original"}, {"id": 9, "bbox": [[368, 131], [372, 131], [372, 147], [368, 147]], "text": "-", "confidence": 0.949999988079071, "status": "ARGUS_original"}, {"id": 10, "bbox": [[380, 131], [439, 131], [439, 147], [380, 147]], "text": "BARCELONA", "confidence": 0.9800000190734863, "status": "ARGUS_original"}, {"id": 11, "bbox": [[326, 158], [364, 158], [364, 173], [326, 173]], "text": "Espalla", "confidence": 0.7200000286102295, "status": "ARGUS_original"}, {"id": 12, "bbox": [[328, 179], [346, 179], [346, 196], [328, 196]], "text": "Tif", "confidence": 0.6499999761581421, "status": "ARGUS_original"}, {"id": 13, "bbox": [[348, 178], [352, 178], [352, 195], [348, 195]], "text": ":", "confidence": 0.8999999761581421, "status": "ARGUS_original"}, {"id": 14, "bbox": [[362, 178], [366, 178], [366, 195], [362, 195]], "text": "+", "confidence": 0.4099999964237213, "status": "ARGUS_original"}, {"id": 15, "bbox": [[370, 177], [428, 176], [428, 194], [370, 195]], "text": "933220611", "confidence": 0.7799999713897705, "status": "ARGUS_original"}, {"id": 16, "bbox": [[442, 177], [463, 177], [463, 194], [442, 194]], "text": "Fax", "confidence": 0.8600000143051147, "status": "ARGUS_original"}, {"id": 17, "bbox": [[463, 177], [467, 177], [467, 194], [463, 194]], "text": ":", "confidence": 1.0, "status": "ARGUS_original"}, {"id": 18, "bbox": [[477, 177], [481, 177], [481, 194], [477, 194]], "text": "+", "confidence": 0.9900000095367432, "status": "ARGUS_original"}, {"id": 19, "bbox": [[484, 176], [545, 175], [545, 193], [484, 194]], "text": "93322090B", "confidence": 0.9700000286102295, "status": "ARGUS_original"}, {"id": 20, "bbox": [[326, 205], [413, 205], [413, 220], [326, 220]], "text": "nhlescortsenh", "confidence": 0.800000011920929, "status": "ARGUS_original"}, {"id": 21, "bbox": [[417, 204], [420, 204], [420, 219], [417, 219]], "text": "-", "confidence": 0.800000011920929, "status": "ARGUS_original"}, {"id": 22, "bbox": [[422, 204], [461, 204], [461, 219], [422, 219]], "text": "hotels", "confidence": 0.949999988079071, "status": "ARGUS_original"}, {"id": 23, "bbox": [[465, 204], [468, 204], [468, 219], [465, 219]], "text": ".", "confidence": 0.9900000095367432, "status": "ARGUS_original"}, {"id": 24, "bbox": [[470, 204], [488, 204], [488, 219], [470, 219]], "text": "com", "confidence": 0.9900000095367432, "status": "ARGUS_original"}, {"id": 25, "bbox": [[119, 162], [154, 162], [154, 177], [119, 177]], "text": "www", "confidence": 0.9900000095367432, "status": "ARGUS_original"}, {"id": 26, "bbox": [[157, 162], [160, 162], [160, 177], [157, 177]], "text": ".", "confidence": 1.0, "status": "ARGUS_original"}, {"id": 27, "bbox": [[161, 161], [175, 161], [175, 176], [161, 176]], "text": "nh", "confidence": 0.9900000095367432, "status": "ARGUS_original"}, {"id": 28, "bbox": [[180, 161], [183, 161], [183, 176], [180, 176]], "text": "-", "confidence": 0.9900000095367432, "status": "ARGUS_original"}, {"id": 29, "bbox": [[185, 161], [226, 161], [226, 176], [185, 176]], "text": "hotels", "confidence": 0.9900000095367432, "status": "ARGUS_original"}, {"id": 30, "bbox": [[228, 161], [231, 161], [231, 176], [228, 176]], "text": ".", "confidence": 0.9800000190734863, "status": "ARGUS_original"}, {"id": 31, "bbox": [[233, 161], [255, 161], [255, 176], [233, 176]], "text": "com", "confidence": 0.9900000095367432, "status": "ARGUS_original"}, {"id": 32, "bbox": [[1035, 146], [1124, 146], [1124, 169], [1035, 169]], "text": "HOTELS", "confidence": 0.9900000095367432, "status": "ARGUS_original"}, {"id": 33, "bbox": [[92, 254], [126, 254], [126, 271], [92, 271]], "text": "Datos", "confidence": 0.9800000190734863, "status": "ARGUS_original"}, {"id": 34, "bbox": [[135, 254], [189, 254], [189, 271], [135, 271]], "text": "fiscales", "confidence": 0.9900000095367432, "status": "ARGUS_original"}, {"id": 35, "bbox": [[94, 275], [156, 275], [156, 289], [94, 289]], "text": "879217790", "confidence": 0.949999988079071, "status": "ARGUS_original"}, {"id": 36, "bbox": [[89, 292], [165, 292], [165, 307], [89, 307]], "text": "ACCENTURE", "confidence": 0.9900000095367432, "status": "ARGUS_original"}, {"id": 37, "bbox": [[169, 291], [183, 291], [183, 306], [169, 306]], "text": "SL", "confidence": 0.9900000095367432, "status": "ARGUS_original"}, {"id": 38, "bbox": [[89, 313], [104, 313], [104, 326], [89, 326]], "text": "DE", "confidence": 0.9900000095367432, "status": "ARGUS_original"}, {"id": 39, "bbox": [[109, 313], [121, 313], [121, 326], [109, 326]], "text": "LA", "confidence": 1.0, "status": "ARGUS_original"}, {"id": 40, "bbox": [[129, 313], [163, 313], [163, 326], [129, 326]], "text": "FINCA", "confidence": 0.9900000095367432, "status": "ARGUS_original"}, {"id": 41, "bbox": [[170, 312], [173, 312], [173, 325], [170, 325]], "text": "1", "confidence": 0.9599999785423279, "status": "ARGUS_original"}, {"id": 42, "bbox": [[90, 331], [123, 331], [123, 345], [90, 345]], "text": "29223", "confidence": 0.8399999737739563, "status": "ARGUS_original"}, {"id": 43, "bbox": [[86, 348], [142, 348], [142, 363], [86, 363]], "text": "POZUELO", "confidence": 0.9900000095367432, "status": "ARGUS_original"}, {"id": 44, "bbox": [[150, 348], [164, 348], [164, 363], [150, 363]], "text": "DE", "confidence": 0.9900000095367432, "status": "ARGUS_original"}, {"id": 45, "bbox": [[170, 347], [225, 347], [225, 362], [170, 362]], "text": "ALARCON", "confidence": 0.9900000095367432, "status": "ARGUS_original"}, {"id": 46, "bbox": [[234, 347], [237, 347], [237, 362], [234, 362]], "text": "-", "confidence": 0.9700000286102295, "status": "ARGUS_original"}, {"id": 47, "bbox": [[243, 347], [281, 347], [281, 362], [243, 362]], "text": "Espalla", "confidence": 0.8600000143051147, "status": "ARGUS_original"}, {"id": 48, "bbox": [[86, 366], [113, 366], [113, 381], [86, 381]], "text": "Party", "confidence": 0.8799999952316284, "status": "ARGUS_original"}, {"id": 49, "bbox": [[119, 366], [187, 366], [187, 381], [119, 381]], "text": "2000073787", "confidence": 0.949999988079071, "status": "ARGUS_original"}, {"id": 50, "bbox": [[207, 365], [256, 365], [256, 380], [207, 380]], "text": "Sucursal", "confidence": 0.8899999856948853, "status": "ARGUS_original"}, {"id": 51, "bbox": [[260, 365], [329, 365], [329, 380], [260, 380]], "text": "0004425139", "confidence": 0.9200000166893005, "status": "ARGUS_original"}, {"id": 52, "bbox": [[85, 386], [129, 385], [129, 400], [85, 401]], "text": "Reserva", "confidence": 0.9900000095367432, "status": "ARGUS_original"}, {"id": 53, "bbox": [[136, 385], [205, 384], [205, 400], [136, 401]], "text": "0033791043", "confidence": 0.9900000095367432, "status": "ARGUS_original"}, {"id": 54, "bbox": [[236, 384], [264, 384], [264, 399], [236, 399]], "text": "Bono", "confidence": 0.9100000262260437, "status": "ARGUS_original"}, {"id": 55, "bbox": [[269, 383], [319, 382], [319, 397], [269, 398]], "text": "oOXVAP", "confidence": 0.5, "status": "ARGUS_original"}, {"id": 56, "bbox": [[697, 253], [731, 253], [731, 267], [697, 267]], "text": "Datos", "confidence": 0.9900000095367432, "status": "ARGUS_original"}, {"id": 57, "bbox": [[740, 252], [792, 252], [792, 266], [740, 266]], "text": "postales", "confidence": 0.9900000095367432, "status": "ARGUS_original"}, {"id": 58, "bbox": [[697, 270], [771, 270], [771, 285], [697, 285]], "text": "ACCENTURE", "confidence": 0.9900000095367432, "status": "ARGUS_original"}, {"id": 59, "bbox": [[778, 269], [789, 269], [789, 284], [778, 284]], "text": "SL", "confidence": 0.9700000286102295, "status": "ARGUS_original"}, {"id": 60, "bbox": [[699, 290], [702, 290], [702, 303], [699, 303]], "text": "T", "confidence": 0.9800000190734863, "status": "ARGUS_original"}, {"id": 61, "bbox": [[705, 290], [708, 290], [708, 303], [705, 303]], "text": ".", "confidence": 0.9599999785423279, "status": "ARGUS_original"}, {"id": 62, "bbox": [[708, 290], [759, 290], [759, 303], [708, 303]], "text": "PICASSO", "confidence": 0.9800000190734863, "status": "ARGUS_original"}, {"id": 63, "bbox": [[766, 289], [778, 289], [778, 302], [766, 302]], "text": "PL", "confidence": 0.9900000095367432, "status": "ARGUS_original"}, {"id": 64, "bbox": [[779, 289], [782, 289], [782, 302], [779, 302]], "text": ".", "confidence": 0.9900000095367432, "status": "ARGUS_original"}, {"id": 65, "bbox": [[787, 289], [799, 289], [799, 302], [787, 302]], "text": "31", "confidence": 0.9300000071525574, "status": "ARGUS_original"}, {"id": 66, "bbox": [[805, 289], [819, 289], [819, 302], [805, 302]], "text": "SIN", "confidence": 0.800000011920929, "status": "ARGUS_original"}, {"id": 67, "bbox": [[700, 308], [731, 308], [731, 321], [700, 321]], "text": "28020", "confidence": 0.9200000166893005, "status": "ARGUS_original"}, {"id": 68, "bbox": [[697, 326], [743, 326], [743, 341], [697, 341]], "text": "MADAID", "confidence": 0.9900000095367432, "status": "ARGUS_original"}, {"id": 69, "bbox": [[751, 325], [754, 325], [754, 340], [751, 340]], "text": "-", "confidence": 0.25, "status": "ARGUS_original"}, {"id": 70, "bbox": [[758, 325], [801, 325], [801, 340], [758, 340]], "text": "Espana", "confidence": 0.7699999809265137, "status": "ARGUS_original"}, {"id": 71, "bbox": [[928, 490], [962, 489], [963, 504], [929, 505]], "text": "Fecha", "confidence": 0.9900000095367432, "status": "ARGUS_original"}, {"id": 72, "bbox": [[970, 489], [992, 488], [993, 503], [971, 504]], "text": "OUT", "confidence": 0.9399999976158142, "status": "ARGUS_original"}, {"id": 73, "bbox": [[72, 493], [92, 493], [92, 516], [72, 516]], "text": "Nur", "confidence": 0.6600000262260437, "status": "ARGUS_original"}, {"id": 74, "bbox": [[96, 493], [102, 493], [102, 516], [96, 516]], "text": ".", "confidence": 0.6700000166893005, "status": "ARGUS_original"}, {"id": 75, "bbox": [[111, 493], [159, 493], [159, 516], [111, 516]], "text": "Facture", "confidence": 0.75, "status": "ARGUS_original"}, {"id": 76, "bbox": [[72, 521], [145, 521], [145, 538], [72, 538]], "text": "4104041644", "confidence": 0.9800000190734863, "status": "ARGUS_original"}, {"id": 77, "bbox": [[442, 491], [462, 491], [462, 514], [442, 514]], "text": "PAX", "confidence": 0.9300000071525574, "status": "ARGUS_original"}, {"id": 78, "bbox": [[1080, 488], [1123, 490], [1122, 507], [1079, 505]], "text": "P\u00e1gina", "confidence": 0.8199999928474426, "status": "ARGUS_original"}, {"id": 79, "bbox": [[197, 492], [231, 492], [231, 515], [197, 515]], "text": "Fecha", "confidence": 0.7400000095367432, "status": "ARGUS_original"}, {"id": 80, "bbox": [[196, 520], [210, 520], [210, 538], [196, 538]], "text": "01", "confidence": 0.9900000095367432, "status": "ARGUS_original"}, {"id": 81, "bbox": [[213, 520], [217, 520], [217, 538], [213, 538]], "text": ".", "confidence": 0.9900000095367432, "status": "ARGUS_original"}, {"id": 82, "bbox": [[217, 520], [231, 520], [231, 538], [217, 538]], "text": "06", "confidence": 0.9900000095367432, "status": "ARGUS_original"}, {"id": 83, "bbox": [[236, 520], [240, 520], [240, 538], [236, 538]], "text": ".", "confidence": 1.0, "status": "ARGUS_original"}, {"id": 84, "bbox": [[240, 520], [269, 520], [269, 538], [240, 538]], "text": "2017", "confidence": 0.9900000095367432, "status": "ARGUS_original"}, {"id": 85, "bbox": [[319, 492], [390, 492], [390, 515], [319, 515]], "text": "Habitaci\u00f3n", "confidence": 0.800000011920929, "status": "ARGUS_original"}, {"id": 86, "bbox": [[320, 521], [340, 521], [340, 539], [320, 539]], "text": "201", "confidence": 0.9900000095367432, "status": "ARGUS_original"}, {"id": 87, "bbox": [[502, 491], [543, 491], [543, 514], [502, 514]], "text": "Nombre", "confidence": 0.9900000095367432, "status": "ARGUS_original"}, {"id": 88, "bbox": [[502, 520], [542, 520], [542, 538], [502, 538]], "text": "ALICIA", "confidence": 0.9900000095367432, "status": "ARGUS_original"}, {"id": 89, "bbox": [[553, 519], [609, 519], [609, 537], [553, 537]], "text": "GONZALEZ", "confidence": 0.9900000095367432, "status": "ARGUS_original"}, {"id": 90, "bbox": [[616, 519], [658, 519], [658, 537], [616, 537]], "text": "MORENO", "confidence": 0.9900000095367432, "status": "ARGUS_original"}, {"id": 91, "bbox": [[805, 491], [842, 491], [842, 507], [805, 507]], "text": "Fecha", "confidence": 0.9900000095367432, "status": "ARGUS_original"}, {"id": 92, "bbox": [[850, 491], [862, 491], [862, 507], [850, 507]], "text": "IN", "confidence": 0.9800000190734863, "status": "ARGUS_original"}, {"id": 93, "bbox": [[808, 515], [820, 515], [820, 538], [808, 538]], "text": "29", "confidence": 0.9900000095367432, "status": "ARGUS_original"}, {"id": 94, "bbox": [[822, 515], [828, 515], [828, 538], [822, 538]], "text": ".", "confidence": 0.9900000095367432, "status": "ARGUS_original"}, {"id": 95, "bbox": [[830, 515], [842, 515], [842, 538], [830, 538]], "text": "05", "confidence": 0.9900000095367432, "status": "ARGUS_original"}, {"id": 96, "bbox": [[844, 515], [850, 515], [850, 538], [844, 538]], "text": ".", "confidence": 1.0, "status": "ARGUS_original"}, {"id": 97, "bbox": [[851, 515], [878, 515], [878, 538], [851, 538]], "text": "2017", "confidence": 0.9900000095367432, "status": "ARGUS_original"}, {"id": 98, "bbox": [[927, 516], [943, 516], [943, 533], [927, 533]], "text": "01", "confidence": 0.9900000095367432, "status": "ARGUS_original"}, {"id": 99, "bbox": [[943, 516], [947, 516], [947, 533], [943, 533]], "text": ".", "confidence": 0.9900000095367432, "status": "ARGUS_original"}, {"id": 100, "bbox": [[950, 516], [962, 516], [962, 533], [950, 533]], "text": "06", "confidence": 0.9900000095367432, "status": "ARGUS_original"}, {"id": 101, "bbox": [[966, 516], [970, 516], [970, 533], [966, 533]], "text": ".", "confidence": 0.9900000095367432, "status": "ARGUS_original"}, {"id": 102, "bbox": [[973, 516], [997, 516], [997, 533], [973, 533]], "text": "2017", "confidence": 0.9900000095367432, "status": "ARGUS_original"}, {"id": 103, "bbox": [[1083, 517], [1086, 517], [1086, 531], [1083, 531]], "text": "1", "confidence": 0.9900000095367432, "status": "ARGUS_original"}, {"id": 104, "bbox": [[1089, 517], [1092, 517], [1092, 531], [1089, 531]], "text": "/", "confidence": 0.9900000095367432, "status": "ARGUS_original"}, {"id": 105, "bbox": [[1097, 517], [1100, 517], [1100, 531], [1097, 531]], "text": "1", "confidence": 0.9900000095367432, "status": "ARGUS_original"}, {"id": 106, "bbox": [[179, 589], [215, 589], [215, 603], [179, 603]], "text": "Fecha", "confidence": 0.9700000286102295, "status": "ARGUS_original"}, {"id": 107, "bbox": [[929, 585], [964, 585], [964, 599], [929, 599]], "text": "Cuota", "confidence": 0.9900000095367432, "status": "ARGUS_original"}, {"id": 108, "bbox": [[758, 585], [783, 585], [783, 606], [758, 606]], "text": "XIVA", "confidence": 0.7099999785423279, "status": "ARGUS_original"}, {"id": 109, "bbox": [[766, 613], [776, 613], [776, 632], [766, 632]], "text": "10", "confidence": 0.9900000095367432, "status": "ARGUS_original"}, {"id": 110, "bbox": [[780, 613], [785, 613], [785, 632], [780, 632]], "text": "%", "confidence": 0.05999999865889549, "status": "ARGUS_original"}, {"id": 111, "bbox": [[184, 616], [196, 616], [196, 633], [184, 633]], "text": "29", "confidence": 0.9900000095367432, "status": "ARGUS_original"}, {"id": 112, "bbox": [[199, 616], [203, 616], [203, 633], [199, 633]], "text": ".", "confidence": 0.9900000095367432, "status": "ARGUS_original"}, {"id": 113, "bbox": [[206, 616], [218, 616], [218, 633], [206, 633]], "text": "05", "confidence": 0.9900000095367432, "status": "ARGUS_original"}, {"id": 114, "bbox": [[220, 616], [224, 616], [224, 633], [220, 633]], "text": ".", "confidence": 1.0, "status": "ARGUS_original"}, {"id": 115, "bbox": [[226, 616], [253, 616], [253, 633], [226, 633]], "text": "2017", "confidence": 0.9900000095367432, "status": "ARGUS_original"}, {"id": 116, "bbox": [[939, 611], [943, 611], [941, 629], [937, 629]], "text": "8", "confidence": 0.9900000095367432, "status": "ARGUS_original"}, {"id": 117, "bbox": [[947, 612], [951, 612], [949, 630], [945, 630]], "text": ".", "confidence": 0.9800000190734863, "status": "ARGUS_original"}, {"id": 118, "bbox": [[952, 612], [964, 613], [962, 631], [950, 630]], "text": "55", "confidence": 0.949999988079071, "status": "ARGUS_original"}, {"id": 119, "bbox": [[301, 588], [328, 588], [328, 609], [301, 609]], "text": "Cant", "confidence": 0.9900000095367432, "status": "ARGUS_original"}, {"id": 120, "bbox": [[333, 588], [338, 588], [338, 609], [333, 609]], "text": ".", "confidence": 0.9900000095367432, "status": "ARGUS_original"}, {"id": 121, "bbox": [[332, 617], [336, 617], [336, 635], [332, 635]], "text": "1", "confidence": 0.5099999904632568, "status": "ARGUS_original"}, {"id": 122, "bbox": [[335, 646], [339, 646], [339, 664], [335, 664]], "text": "1", "confidence": 0.8700000047683716, "status": "ARGUS_original"}, {"id": 123, "bbox": [[337, 675], [341, 675], [341, 692], [337, 692]], "text": "1", "confidence": 0.699999988079071, "status": "ARGUS_original"}, {"id": 124, "bbox": [[187, 646], [198, 646], [198, 662], [187, 662]], "text": "29", "confidence": 0.9900000095367432, "status": "ARGUS_original"}, {"id": 125, "bbox": [[202, 646], [206, 646], [206, 662], [202, 662]], "text": ".", "confidence": 1.0, "status": "ARGUS_original"}, {"id": 126, "bbox": [[206, 646], [220, 646], [220, 662], [206, 662]], "text": "05", "confidence": 1.0, "status": "ARGUS_original"}, {"id": 127, "bbox": [[222, 646], [226, 646], [226, 662], [222, 662]], "text": ".", "confidence": 1.0, "status": "ARGUS_original"}, {"id": 128, "bbox": [[229, 646], [255, 646], [255, 662], [229, 662]], "text": "2017", "confidence": 0.9900000095367432, "status": "ARGUS_original"}, {"id": 129, "bbox": [[765, 643], [783, 641], [786, 661], [768, 664]], "text": "107", "confidence": 0.6700000166893005, "status": "ARGUS_original"}, {"id": 130, "bbox": [[936, 641], [941, 641], [941, 660], [936, 660]], "text": "0", "confidence": 0.9900000095367432, "status": "ARGUS_original"}, {"id": 131, "bbox": [[944, 641], [949, 641], [949, 660], [944, 660]], "text": ".", "confidence": 0.9900000095367432, "status": "ARGUS_original"}, {"id": 132, "bbox": [[949, 641], [963, 641], [963, 660], [949, 660]], "text": "07", "confidence": 0.9700000286102295, "status": "ARGUS_original"}, {"id": 133, "bbox": [[364, 587], [418, 587], [418, 608], [364, 608]], "text": "Servicio", "confidence": 0.9700000286102295, "status": "ARGUS_original"}, {"id": 134, "bbox": [[367, 616], [391, 616], [391, 634], [367, 634]], "text": "5010", "confidence": 0.7300000190734863, "status": "ARGUS_original"}, {"id": 135, "bbox": [[401, 616], [470, 616], [470, 634], [401, 634]], "text": "habitaci\u00f3n", "confidence": 0.9300000071525574, "status": "ARGUS_original"}, {"id": 136, "bbox": [[369, 645], [392, 645], [392, 663], [369, 663]], "text": "Tasa", "confidence": 0.9399999976158142, "status": "ARGUS_original"}, {"id": 137, "bbox": [[403, 645], [465, 645], [465, 663], [403, 663]], "text": "turistica", "confidence": 0.9100000262260437, "status": "ARGUS_original"}, {"id": 138, "bbox": [[371, 675], [395, 675], [395, 692], [371, 692]], "text": "5010", "confidence": 0.5799999833106995, "status": "ARGUS_original"}, {"id": 139, "bbox": [[404, 675], [472, 676], [472, 694], [404, 693]], "text": "habitacion", "confidence": 0.800000011920929, "status": "ARGUS_original"}, {"id": 140, "bbox": [[371, 704], [396, 704], [396, 721], [371, 721]], "text": "Tasa", "confidence": 0.9399999976158142, "status": "ARGUS_original"}, {"id": 141, "bbox": [[405, 704], [466, 704], [466, 721], [405, 721]], "text": "turistica", "confidence": 0.9800000190734863, "status": "ARGUS_original"}, {"id": 142, "bbox": [[371, 732], [397, 732], [397, 750], [371, 750]], "text": "S\u00f3lo", "confidence": 0.41999998688697815, "status": "ARGUS_original"}, {"id": 143, "bbox": [[406, 732], [472, 732], [472, 750], [406, 750]], "text": "habitacion", "confidence": 0.8700000047683716, "status": "ARGUS_original"}, {"id": 144, "bbox": [[375, 761], [399, 761], [399, 778], [375, 778]], "text": "Tasa", "confidence": 0.9399999976158142, "status": "ARGUS_original"}, {"id": 145, "bbox": [[409, 761], [466, 762], [466, 780], [409, 779]], "text": "turistica", "confidence": 0.9300000071525574, "status": "ARGUS_original"}, {"id": 146, "bbox": [[845, 584], [874, 584], [874, 602], [845, 602]], "text": "Base", "confidence": 0.9900000095367432, "status": "ARGUS_original"}, {"id": 147, "bbox": [[841, 613], [851, 613], [851, 632], [841, 632]], "text": "85", "confidence": 0.9900000095367432, "status": "ARGUS_original"}, {"id": 148, "bbox": [[855, 613], [860, 613], [860, 632], [855, 632]], "text": ".", "confidence": 0.9900000095367432, "status": "ARGUS_original"}, {"id": 149, "bbox": [[860, 613], [874, 613], [874, 632], [860, 632]], "text": "50", "confidence": 0.9700000286102295, "status": "ARGUS_original"}, {"id": 150, "bbox": [[846, 643], [850, 643], [850, 661], [846, 661]], "text": "0", "confidence": 0.9900000095367432, "status": "ARGUS_original"}, {"id": 151, "bbox": [[854, 643], [858, 643], [858, 661], [854, 661]], "text": ".", "confidence": 0.9900000095367432, "status": "ARGUS_original"}, {"id": 152, "bbox": [[862, 643], [871, 643], [871, 661], [862, 661]], "text": "65", "confidence": 0.9900000095367432, "status": "ARGUS_original"}, {"id": 153, "bbox": [[839, 672], [849, 672], [849, 690], [839, 690]], "text": "85", "confidence": 0.9900000095367432, "status": "ARGUS_original"}, {"id": 154, "bbox": [[853, 672], [857, 672], [857, 690], [853, 690]], "text": ".", "confidence": 0.9800000190734863, "status": "ARGUS_original"}, {"id": 155, "bbox": [[859, 672], [873, 672], [873, 690], [859, 690]], "text": "50", "confidence": 0.7400000095367432, "status": "ARGUS_original"}, {"id": 156, "bbox": [[846, 701], [850, 701], [850, 717], [846, 717]], "text": "0", "confidence": 0.9700000286102295, "status": "ARGUS_original"}, {"id": 157, "bbox": [[853, 701], [857, 701], [857, 717], [853, 717]], "text": ".", "confidence": 0.9399999976158142, "status": "ARGUS_original"}, {"id": 158, "bbox": [[860, 701], [871, 701], [871, 717], [860, 717]], "text": "65", "confidence": 0.9599999785423279, "status": "ARGUS_original"}, {"id": 159, "bbox": [[837, 728], [851, 728], [851, 747], [837, 747]], "text": "85", "confidence": 0.9300000071525574, "status": "ARGUS_original"}, {"id": 160, "bbox": [[852, 728], [857, 728], [857, 747], [852, 747]], "text": ".", "confidence": 0.5099999904632568, "status": "ARGUS_original"}, {"id": 161, "bbox": [[860, 728], [870, 728], [870, 747], [860, 747]], "text": "50", "confidence": 0.8999999761581421, "status": "ARGUS_original"}, {"id": 162, "bbox": [[845, 756], [850, 756], [850, 775], [845, 775]], "text": "0", "confidence": 0.9700000286102295, "status": "ARGUS_original"}, {"id": 163, "bbox": [[853, 756], [858, 756], [858, 775], [853, 775]], "text": ".", "confidence": 0.46000000834465027, "status": "ARGUS_original"}, {"id": 164, "bbox": [[859, 756], [869, 756], [869, 775], [859, 775]], "text": "65", "confidence": 0.8100000023841858, "status": "ARGUS_original"}, {"id": 165, "bbox": [[188, 676], [199, 676], [199, 692], [188, 692]], "text": "30", "confidence": 0.9900000095367432, "status": "ARGUS_original"}, {"id": 166, "bbox": [[203, 676], [207, 676], [207, 692], [203, 692]], "text": ".", "confidence": 0.9900000095367432, "status": "ARGUS_original"}, {"id": 167, "bbox": [[210, 676], [221, 676], [221, 692], [210, 692]], "text": "05", "confidence": 0.9900000095367432, "status": "ARGUS_original"}, {"id": 168, "bbox": [[225, 676], [229, 676], [229, 692], [225, 692]], "text": ".", "confidence": 1.0, "status": "ARGUS_original"}, {"id": 169, "bbox": [[232, 676], [256, 676], [256, 692], [232, 692]], "text": "2017", "confidence": 0.9900000095367432, "status": "ARGUS_original"}, {"id": 170, "bbox": [[188, 704], [202, 704], [202, 719], [188, 719]], "text": "30", "confidence": 0.9900000095367432, "status": "ARGUS_original"}, {"id": 171, "bbox": [[206, 704], [209, 704], [209, 719], [206, 719]], "text": ".", "confidence": 0.9900000095367432, "status": "ARGUS_original"}, {"id": 172, "bbox": [[212, 704], [223, 704], [223, 719], [212, 719]], "text": "05", "confidence": 0.9900000095367432, "status": "ARGUS_original"}, {"id": 173, "bbox": [[227, 704], [230, 704], [230, 719], [227, 719]], "text": ".", "confidence": 0.6899999976158142, "status": "ARGUS_original"}, {"id": 174, "bbox": [[234, 704], [260, 704], [260, 719], [234, 719]], "text": "2017", "confidence": 0.9700000286102295, "status": "ARGUS_original"}, {"id": 175, "bbox": [[1141, 581], [1173, 581], [1173, 599], [1141, 599]], "text": "Saldo", "confidence": 0.9900000095367432, "status": "ARGUS_original"}, {"id": 176, "bbox": [[1140, 611], [1150, 611], [1150, 629], [1140, 629]], "text": "94", "confidence": 0.9900000095367432, "status": "ARGUS_original"}, {"id": 177, "bbox": [[1154, 611], [1158, 611], [1158, 629], [1154, 629]], "text": ".", "confidence": 0.8500000238418579, "status": "ARGUS_original"}, {"id": 178, "bbox": [[1160, 611], [1174, 611], [1174, 629], [1160, 629]], "text": "05", "confidence": 0.8999999761581421, "status": "ARGUS_original"}, {"id": 179, "bbox": [[1138, 641], [1149, 641], [1149, 657], [1138, 657]], "text": "94", "confidence": 0.9900000095367432, "status": "ARGUS_original"}, {"id": 180, "bbox": [[1151, 641], [1155, 641], [1155, 657], [1151, 657]], "text": ".", "confidence": 0.38999998569488525, "status": "ARGUS_original"}, {"id": 181, "bbox": [[1160, 641], [1171, 641], [1171, 657], [1160, 657]], "text": "77", "confidence": 0.9200000166893005, "status": "ARGUS_original"}, {"id": 182, "bbox": [[1129, 667], [1149, 667], [1149, 690], [1129, 690]], "text": "188", "confidence": 0.9900000095367432, "status": "ARGUS_original"}, {"id": 183, "bbox": [[1150, 667], [1156, 667], [1156, 690], [1150, 690]], "text": ",", "confidence": 0.6800000071525574, "status": "ARGUS_original"}, {"id": 184, "bbox": [[1158, 667], [1171, 667], [1171, 690], [1158, 690]], "text": "82", "confidence": 0.9100000262260437, "status": "ARGUS_original"}, {"id": 185, "bbox": [[1129, 698], [1147, 698], [1147, 715], [1129, 715]], "text": "189", "confidence": 0.9800000190734863, "status": "ARGUS_original"}, {"id": 186, "bbox": [[1149, 698], [1153, 698], [1153, 715], [1149, 715]], "text": ".", "confidence": 0.6700000166893005, "status": "ARGUS_original"}, {"id": 187, "bbox": [[1156, 698], [1168, 698], [1168, 715], [1156, 715]], "text": "54", "confidence": 0.949999988079071, "status": "ARGUS_original"}, {"id": 188, "bbox": [[1127, 727], [1146, 727], [1146, 744], [1127, 744]], "text": "283", "confidence": 0.8600000143051147, "status": "ARGUS_original"}, {"id": 189, "bbox": [[1149, 727], [1153, 727], [1153, 744], [1149, 744]], "text": ",", "confidence": 0.9800000190734863, "status": "ARGUS_original"}, {"id": 190, "bbox": [[1156, 727], [1168, 727], [1168, 744], [1156, 744]], "text": "56", "confidence": 0.9399999976158142, "status": "ARGUS_original"}, {"id": 191, "bbox": [[936, 669], [941, 669], [942, 690], [937, 690]], "text": "8", "confidence": 0.9900000095367432, "status": "ARGUS_original"}, {"id": 192, "bbox": [[942, 669], [947, 669], [948, 690], [943, 690]], "text": ".", "confidence": 0.5699999928474426, "status": "ARGUS_original"}, {"id": 193, "bbox": [[950, 668], [960, 667], [961, 688], [951, 689]], "text": "55", "confidence": 0.9399999976158142, "status": "ARGUS_original"}, {"id": 194, "bbox": [[1021, 582], [1055, 582], [1055, 599], [1021, 599]], "text": "Total", "confidence": 0.9900000095367432, "status": "ARGUS_original"}, {"id": 195, "bbox": [[1020, 612], [1032, 612], [1032, 629], [1020, 629]], "text": "94", "confidence": 0.9900000095367432, "status": "ARGUS_original"}, {"id": 196, "bbox": [[1035, 612], [1039, 612], [1039, 629], [1035, 629]], "text": ",", "confidence": 0.6200000047683716, "status": "ARGUS_original"}, {"id": 197, "bbox": [[1042, 612], [1054, 612], [1054, 629], [1042, 629]], "text": "05", "confidence": 0.9599999785423279, "status": "ARGUS_original"}, {"id": 198, "bbox": [[1025, 640], [1029, 640], [1029, 658], [1025, 658]], "text": "0", "confidence": 0.9900000095367432, "status": "ARGUS_original"}, {"id": 199, "bbox": [[1033, 640], [1037, 640], [1037, 658], [1033, 658]], "text": ".", "confidence": 0.9300000071525574, "status": "ARGUS_original"}, {"id": 200, "bbox": [[1041, 640], [1053, 640], [1053, 658], [1041, 658]], "text": "72", "confidence": 0.9599999785423279, "status": "ARGUS_original"}, {"id": 201, "bbox": [[1020, 667], [1028, 667], [1029, 690], [1021, 690]], "text": "94", "confidence": 0.9900000095367432, "status": "ARGUS_original"}, {"id": 202, "bbox": [[1031, 667], [1037, 667], [1038, 690], [1032, 690]], "text": ",", "confidence": 0.4099999964237213, "status": "ARGUS_original"}, {"id": 203, "bbox": [[1039, 666], [1051, 665], [1052, 688], [1040, 689]], "text": "05", "confidence": 0.9599999785423279, "status": "ARGUS_original"}, {"id": 204, "bbox": [[1023, 699], [1027, 699], [1027, 717], [1023, 717]], "text": "0", "confidence": 0.9900000095367432, "status": "ARGUS_original"}, {"id": 205, "bbox": [[1031, 699], [1035, 699], [1035, 717], [1031, 717]], "text": ".", "confidence": 0.9700000286102295, "status": "ARGUS_original"}, {"id": 206, "bbox": [[1039, 699], [1051, 699], [1051, 717], [1039, 717]], "text": "72", "confidence": 0.9800000190734863, "status": "ARGUS_original"}, {"id": 207, "bbox": [[1024, 698], [1029, 698], [1029, 719], [1024, 719]], "text": "0", "confidence": 0.9700000286102295, "status": "ARGUS_original"}, {"id": 208, "bbox": [[1031, 698], [1036, 698], [1036, 719], [1031, 719]], "text": ".", "confidence": 0.9900000095367432, "status": "ARGUS_original"}, {"id": 209, "bbox": [[1040, 698], [1050, 698], [1050, 719], [1040, 719]], "text": "72", "confidence": 0.9700000286102295, "status": "ARGUS_original"}, {"id": 210, "bbox": [[1015, 728], [1028, 727], [1029, 745], [1016, 746]], "text": "94", "confidence": 0.9900000095367432, "status": "ARGUS_original"}, {"id": 211, "bbox": [[1031, 728], [1035, 728], [1036, 745], [1032, 745]], "text": ".", "confidence": 0.4399999976158142, "status": "ARGUS_original"}, {"id": 212, "bbox": [[1037, 727], [1049, 726], [1050, 743], [1038, 744]], "text": "04", "confidence": 0.9100000262260437, "status": "ARGUS_original"}, {"id": 213, "bbox": [[1019, 726], [1027, 726], [1027, 749], [1019, 749]], "text": "94", "confidence": 0.8399999737739563, "status": "ARGUS_original"}, {"id": 214, "bbox": [[1029, 726], [1035, 726], [1035, 749], [1029, 749]], "text": ".", "confidence": 0.41999998688697815, "status": "ARGUS_original"}, {"id": 215, "bbox": [[1037, 726], [1049, 726], [1049, 749], [1037, 749]], "text": "04", "confidence": 0.75, "status": "ARGUS_original"}, {"id": 216, "bbox": [[1023, 756], [1027, 756], [1027, 773], [1023, 773]], "text": "0", "confidence": 0.9900000095367432, "status": "ARGUS_original"}, {"id": 217, "bbox": [[1030, 756], [1034, 756], [1034, 773], [1030, 773]], "text": ".", "confidence": 0.9900000095367432, "status": "ARGUS_original"}, {"id": 218, "bbox": [[1036, 756], [1049, 756], [1049, 773], [1036, 773]], "text": "72", "confidence": 0.9900000095367432, "status": "ARGUS_original"}, {"id": 219, "bbox": [[1023, 754], [1029, 754], [1029, 777], [1023, 777]], "text": "0", "confidence": 0.9800000190734863, "status": "ARGUS_original"}, {"id": 220, "bbox": [[1030, 754], [1036, 754], [1036, 777], [1030, 777]], "text": ".", "confidence": 0.9800000190734863, "status": "ARGUS_original"}, {"id": 221, "bbox": [[1038, 754], [1050, 754], [1050, 777], [1038, 777]], "text": "72", "confidence": 0.7400000095367432, "status": "ARGUS_original"}, {"id": 222, "bbox": [[764, 699], [776, 699], [776, 722], [764, 722]], "text": "10", "confidence": 0.9700000286102295, "status": "ARGUS_original"}, {"id": 223, "bbox": [[777, 699], [783, 699], [783, 722], [777, 722]], "text": "%", "confidence": 0.9599999785423279, "status": "ARGUS_original"}, {"id": 224, "bbox": [[330, 745], [330, 741], [346, 740], [346, 744]], "text": "-", "confidence": 0.49000000953674316, "status": "ARGUS_original"}, {"id": 225, "bbox": [[193, 732], [204, 732], [204, 753], [193, 753]], "text": "31", "confidence": 0.9900000095367432, "status": "ARGUS_original"}, {"id": 226, "bbox": [[206, 732], [211, 732], [211, 753], [206, 753]], "text": ".", "confidence": 1.0, "status": "ARGUS_original"}, {"id": 227, "bbox": [[212, 732], [227, 732], [227, 753], [212, 753]], "text": "05", "confidence": 0.9900000095367432, "status": "ARGUS_original"}, {"id": 228, "bbox": [[228, 732], [233, 732], [233, 753], [228, 753]], "text": ".", "confidence": 1.0, "status": "ARGUS_original"}, {"id": 229, "bbox": [[235, 732], [262, 732], [262, 753], [235, 753]], "text": "2017", "confidence": 0.9900000095367432, "status": "ARGUS_original"}, {"id": 230, "bbox": [[193, 763], [207, 763], [207, 778], [193, 778]], "text": "31", "confidence": 0.9900000095367432, "status": "ARGUS_original"}, {"id": 231, "bbox": [[209, 763], [212, 763], [212, 778], [209, 778]], "text": ".", "confidence": 0.9900000095367432, "status": "ARGUS_original"}, {"id": 232, "bbox": [[215, 763], [226, 763], [226, 778], [215, 778]], "text": "05", "confidence": 0.9900000095367432, "status": "ARGUS_original"}, {"id": 233, "bbox": [[230, 763], [233, 763], [233, 778], [230, 778]], "text": ".", "confidence": 1.0, "status": "ARGUS_original"}, {"id": 234, "bbox": [[237, 763], [263, 763], [263, 778], [237, 778]], "text": "2017", "confidence": 0.9900000095367432, "status": "ARGUS_original"}, {"id": 235, "bbox": [[339, 733], [343, 733], [343, 751], [339, 751]], "text": "1", "confidence": 0.9900000095367432, "status": "ARGUS_original"}, {"id": 236, "bbox": [[341, 761], [345, 761], [345, 778], [341, 778]], "text": "1", "confidence": 0.7900000214576721, "status": "ARGUS_original"}, {"id": 237, "bbox": [[934, 698], [939, 698], [939, 719], [934, 719]], "text": "0", "confidence": 0.9900000095367432, "status": "ARGUS_original"}, {"id": 238, "bbox": [[943, 698], [948, 698], [948, 719], [943, 719]], "text": ".", "confidence": 0.9900000095367432, "status": "ARGUS_original"}, {"id": 239, "bbox": [[949, 698], [960, 698], [960, 719], [949, 719]], "text": "07", "confidence": 0.9900000095367432, "status": "ARGUS_original"}, {"id": 240, "bbox": [[933, 726], [939, 726], [939, 749], [933, 749]], "text": "8", "confidence": 0.9700000286102295, "status": "ARGUS_original"}, {"id": 241, "bbox": [[941, 726], [947, 726], [947, 749], [941, 749]], "text": ".", "confidence": 0.9900000095367432, "status": "ARGUS_original"}, {"id": 242, "bbox": [[948, 726], [961, 726], [961, 749], [948, 749]], "text": "54", "confidence": 0.9700000286102295, "status": "ARGUS_original"}, {"id": 243, "bbox": [[934, 754], [940, 754], [940, 777], [934, 777]], "text": "0", "confidence": 0.9900000095367432, "status": "ARGUS_original"}, {"id": 244, "bbox": [[941, 754], [947, 754], [947, 777], [941, 777]], "text": ".", "confidence": 1.0, "status": "ARGUS_original"}, {"id": 245, "bbox": [[949, 754], [961, 754], [961, 777], [949, 777]], "text": "07", "confidence": 0.9900000095367432, "status": "ARGUS_original"}, {"id": 246, "bbox": [[763, 757], [777, 757], [777, 776], [763, 776]], "text": "10", "confidence": 0.9900000095367432, "status": "ARGUS_original"}, {"id": 247, "bbox": [[778, 757], [783, 757], [783, 776], [778, 776]], "text": "%", "confidence": 0.11999999731779099, "status": "ARGUS_original"}, {"id": 248, "bbox": [[1125, 758], [1144, 758], [1144, 771], [1125, 771]], "text": "284", "confidence": 0.9900000095367432, "status": "ARGUS_original"}, {"id": 249, "bbox": [[1147, 758], [1150, 758], [1150, 771], [1147, 771]], "text": ",", "confidence": 0.9900000095367432, "status": "ARGUS_original"}, {"id": 250, "bbox": [[1155, 758], [1164, 758], [1164, 771], [1155, 771]], "text": "39", "confidence": 0.6800000071525574, "status": "ARGUS_original"}, {"id": 251, "bbox": [[82, 1097], [80, 1060], [92, 1059], [94, 1096]], "text": "Insoita", "confidence": 0.6399999856948853, "status": "ARGUS_original"}, {"id": 252, "bbox": [[79, 1055], [78, 1045], [90, 1044], [91, 1054]], "text": "en", "confidence": 0.8299999833106995, "status": "ARGUS_original"}, {"id": 253, "bbox": [[78, 1036], [77, 1028], [89, 1027], [90, 1035]], "text": "el", "confidence": 0.8999999761581421, "status": "ARGUS_original"}, {"id": 254, "bbox": [[78, 1026], [75, 983], [87, 982], [90, 1025]], "text": "Registro", "confidence": 0.9399999976158142, "status": "ARGUS_original"}, {"id": 255, "bbox": [[75, 977], [72, 928], [84, 927], [87, 976]], "text": "Mercantil", "confidence": 0.9900000095367432, "status": "ARGUS_original"}, {"id": 256, "bbox": [[71, 924], [70, 912], [81, 911], [82, 923]], "text": "de", "confidence": 0.8899999856948853, "status": "ARGUS_original"}, {"id": 257, "bbox": [[70, 907], [68, 874], [80, 873], [82, 906]], "text": "Madrid", "confidence": 0.8899999856948853, "status": "ARGUS_original"}, {"id": 258, "bbox": [[68, 869], [68, 867], [79, 866], [79, 868]], "text": ",", "confidence": 0.7300000190734863, "status": "ARGUS_original"}, {"id": 259, "bbox": [[67, 860], [65, 832], [77, 831], [79, 859]], "text": "Tomo", "confidence": 0.9100000262260437, "status": "ARGUS_original"}, {"id": 260, "bbox": [[66, 829], [66, 827], [77, 826], [77, 828]], "text": ":", "confidence": 0.6200000047683716, "status": "ARGUS_original"}, {"id": 261, "bbox": [[65, 821], [64, 811], [75, 810], [76, 820]], "text": "32", "confidence": 0.8899999856948853, "status": "ARGUS_original"}, {"id": 262, "bbox": [[64, 808], [64, 806], [75, 805], [75, 807]], "text": ".", "confidence": 0.9100000262260437, "status": "ARGUS_original"}, {"id": 263, "bbox": [[64, 804], [63, 784], [74, 783], [75, 803]], "text": "772", "confidence": 0.9200000166893005, "status": "ARGUS_original"}, {"id": 264, "bbox": [[62, 784], [62, 782], [73, 781], [73, 783]], "text": ",", "confidence": 0.7200000286102295, "status": "ARGUS_original"}, {"id": 265, "bbox": [[61, 775], [60, 752], [71, 751], [73, 774]], "text": "Folio", "confidence": 0.9599999785423279, "status": "ARGUS_original"}, {"id": 266, "bbox": [[59, 739], [58, 721], [69, 720], [70, 738]], "text": "184", "confidence": 0.9100000262260437, "status": "ARGUS_original"}, {"id": 267, "bbox": [[58, 719], [58, 717], [69, 716], [69, 718]], "text": ",", "confidence": 0.5299999713897705, "status": "ARGUS_original"}, {"id": 268, "bbox": [[57, 713], [55, 688], [67, 687], [69, 712]], "text": "Hora", "confidence": 0.6700000166893005, "status": "ARGUS_original"}, {"id": 269, "bbox": [[56, 684], [56, 682], [67, 681], [67, 683]], "text": ":", "confidence": 0.8600000143051147, "status": "ARGUS_original"}, {"id": 270, "bbox": [[56, 676], [56, 674], [67, 673], [67, 675]], "text": "M", "confidence": 0.9300000071525574, "status": "ARGUS_original"}, {"id": 271, "bbox": [[55, 666], [55, 664], [66, 663], [66, 665]], "text": "-", "confidence": 0.8700000047683716, "status": "ARGUS_original"}, {"id": 272, "bbox": [[54, 661], [51, 620], [63, 619], [66, 660]], "text": "589881", "confidence": 0.7799999713897705, "status": "ARGUS_original"}, {"id": 273, "bbox": [[52, 618], [52, 616], [63, 615], [63, 617]], "text": ",", "confidence": 0.9100000262260437, "status": "ARGUS_original"}, {"id": 274, "bbox": [[51, 611], [47, 543], [59, 542], [63, 610]], "text": "Insoipooni", "confidence": 0.6700000166893005, "status": "ARGUS_original"}, {"id": 275, "bbox": [[46, 538], [46, 536], [57, 535], [57, 537]], "text": "z", "confidence": 0.6399999856948853, "status": "ARGUS_original"}, {"id": 276, "bbox": [[758, 837], [784, 837], [784, 853], [758, 853]], "text": "XIVA", "confidence": 0.6499999761581421, "status": "ARGUS_original"}, {"id": 277, "bbox": [[1104, 835], [1139, 833], [1140, 851], [1105, 853]], "text": "Total", "confidence": 0.9900000095367432, "status": "ARGUS_original"}, {"id": 278, "bbox": [[875, 837], [902, 837], [902, 855], [875, 855]], "text": "Base", "confidence": 0.9900000095367432, "status": "ARGUS_original"}, {"id": 279, "bbox": [[862, 865], [880, 865], [880, 881], [862, 881]], "text": "258", "confidence": 0.949999988079071, "status": "ARGUS_original"}, {"id": 280, "bbox": [[882, 865], [886, 865], [886, 881], [882, 881]], "text": ".", "confidence": 0.9599999785423279, "status": "ARGUS_original"}, {"id": 281, "bbox": [[889, 865], [900, 865], [900, 881], [889, 881]], "text": "45", "confidence": 0.9700000286102295, "status": "ARGUS_original"}, {"id": 282, "bbox": [[985, 837], [1020, 837], [1020, 852], [985, 852]], "text": "Cuota", "confidence": 0.9900000095367432, "status": "ARGUS_original"}, {"id": 283, "bbox": [[985, 864], [996, 864], [996, 879], [985, 879]], "text": "25", "confidence": 0.9800000190734863, "status": "ARGUS_original"}, {"id": 284, "bbox": [[1000, 864], [1003, 864], [1003, 879], [1000, 879]], "text": ",", "confidence": 0.9399999976158142, "status": "ARGUS_original"}, {"id": 285, "bbox": [[1008, 864], [1019, 864], [1019, 879], [1008, 879]], "text": "85", "confidence": 0.949999988079071, "status": "ARGUS_original"}, {"id": 286, "bbox": [[745, 866], [755, 866], [755, 881], [745, 881]], "text": "10", "confidence": 0.9900000095367432, "status": "ARGUS_original"}, {"id": 287, "bbox": [[760, 866], [763, 866], [763, 881], [760, 881]], "text": ".", "confidence": 0.9900000095367432, "status": "ARGUS_original"}, {"id": 288, "bbox": [[766, 866], [777, 866], [777, 881], [766, 881]], "text": "00", "confidence": 0.9900000095367432, "status": "ARGUS_original"}, {"id": 289, "bbox": [[781, 866], [784, 866], [784, 881], [781, 881]], "text": "%", "confidence": 0.4000000059604645, "status": "ARGUS_original"}, {"id": 290, "bbox": [[318, 868], [336, 868], [336, 884], [318, 884]], "text": "IVA", "confidence": 0.9900000095367432, "status": "ARGUS_original"}, {"id": 291, "bbox": [[319, 896], [353, 896], [353, 913], [319, 913]], "text": "Total", "confidence": 0.9900000095367432, "status": "ARGUS_original"}, {"id": 292, "bbox": [[1097, 864], [1114, 864], [1114, 879], [1097, 879]], "text": "284", "confidence": 0.8100000023841858, "status": "ARGUS_original"}, {"id": 293, "bbox": [[1118, 864], [1121, 864], [1121, 879], [1118, 879]], "text": ".", "confidence": 0.9800000190734863, "status": "ARGUS_original"}, {"id": 294, "bbox": [[1124, 864], [1135, 864], [1135, 879], [1124, 879]], "text": "30", "confidence": 0.9599999785423279, "status": "ARGUS_original"}, {"id": 295, "bbox": [[1089, 891], [1109, 891], [1109, 906], [1089, 906]], "text": "284", "confidence": 0.9900000095367432, "status": "ARGUS_original"}, {"id": 296, "bbox": [[1112, 891], [1115, 891], [1115, 906], [1112, 906]], "text": ",", "confidence": 0.9900000095367432, "status": "ARGUS_original"}, {"id": 297, "bbox": [[1119, 891], [1130, 891], [1130, 906], [1119, 906]], "text": "30", "confidence": 0.9900000095367432, "status": "ARGUS_original"}, {"id": 298, "bbox": [[1146, 891], [1164, 891], [1164, 906], [1146, 906]], "text": "EUR", "confidence": 0.9900000095367432, "status": "ARGUS_original"}, {"id": 299, "bbox": [[1144, 813], [1174, 813], [1175, 916], [1145, 916]], "text": ".", "confidence": 0.25, "status": "ARGUS_original"}, {"id": 300, "bbox": [[857, 893], [873, 893], [873, 907], [857, 907]], "text": "258", "confidence": 0.9399999976158142, "status": "ARGUS_original"}, {"id": 301, "bbox": [[877, 893], [880, 893], [880, 907], [877, 907]], "text": ".", "confidence": 0.8799999952316284, "status": "ARGUS_original"}, {"id": 302, "bbox": [[884, 893], [894, 893], [894, 907], [884, 907]], "text": "45", "confidence": 0.949999988079071, "status": "ARGUS_original"}, {"id": 303, "bbox": [[980, 893], [991, 893], [991, 908], [980, 908]], "text": "25", "confidence": 0.9900000095367432, "status": "ARGUS_original"}, {"id": 304, "bbox": [[995, 893], [998, 893], [998, 908], [995, 908]], "text": ",", "confidence": 0.6800000071525574, "status": "ARGUS_original"}, {"id": 305, "bbox": [[1001, 893], [1012, 893], [1012, 908], [1001, 908]], "text": "85", "confidence": 0.9399999976158142, "status": "ARGUS_original"}, {"id": 306, "bbox": [[670, 970], [705, 970], [705, 985], [670, 985]], "text": "Forra", "confidence": 0.8600000143051147, "status": "ARGUS_original"}, {"id": 307, "bbox": [[712, 970], [726, 970], [726, 985], [712, 985]], "text": "de", "confidence": 0.9200000166893005, "status": "ARGUS_original"}, {"id": 308, "bbox": [[733, 969], [759, 969], [759, 984], [733, 984]], "text": "pago", "confidence": 0.9200000166893005, "status": "ARGUS_original"}, {"id": 309, "bbox": [[673, 995], [698, 997], [697, 1014], [672, 1013]], "text": "VISA", "confidence": 0.9900000095367432, "status": "ARGUS_original"}, {"id": 310, "bbox": [[1091, 996], [1111, 996], [1111, 1011], [1091, 1011]], "text": "284", "confidence": 0.9900000095367432, "status": "ARGUS_original"}, {"id": 311, "bbox": [[1114, 996], [1117, 996], [1117, 1011], [1114, 1011]], "text": ",", "confidence": 0.7200000286102295, "status": "ARGUS_original"}, {"id": 312, "bbox": [[1121, 996], [1132, 996], [1132, 1011], [1121, 1011]], "text": "30", "confidence": 0.9700000286102295, "status": "ARGUS_original"}, {"id": 313, "bbox": [[1145, 996], [1163, 996], [1163, 1011], [1145, 1011]], "text": "EUR", "confidence": 0.8899999856948853, "status": "ARGUS_original"}, {"id": 314, "bbox": [[39, 1607], [43, 1557], [57, 1558], [54, 1608]], "text": "Hoteles", "confidence": 0.7799999713897705, "status": "ARGUS_original"}, {"id": 315, "bbox": [[44, 1552], [47, 1508], [61, 1509], [58, 1553]], "text": "Espa\u00f1a", "confidence": 0.8999999761581421, "status": "ARGUS_original"}, {"id": 316, "bbox": [[47, 1500], [48, 1487], [62, 1488], [61, 1501]], "text": "SA", "confidence": 0.9900000095367432, "status": "ARGUS_original"}, {"id": 317, "bbox": [[48, 1484], [48, 1481], [62, 1482], [62, 1485]], "text": ".", "confidence": 0.6499999761581421, "status": "ARGUS_original"}, {"id": 318, "bbox": [[48, 1476], [51, 1437], [66, 1438], [63, 1477]], "text": "CEFA", "confidence": 0.75, "status": "ARGUS_original"}, {"id": 319, "bbox": [[52, 1437], [52, 1434], [66, 1435], [66, 1438]], "text": "-", "confidence": 0.8199999928474426, "status": "ARGUS_original"}, {"id": 320, "bbox": [[52, 1432], [56, 1371], [70, 1372], [66, 1433]], "text": "38511882", "confidence": 0.6000000238418579, "status": "ARGUS_original"}, {"id": 321, "bbox": [[57, 1368], [57, 1365], [71, 1366], [71, 1369]], "text": ".", "confidence": 0.17000000178813934, "status": "ARGUS_original"}, {"id": 322, "bbox": [[57, 1361], [61, 1310], [76, 1311], [72, 1362]], "text": "Domicilio", "confidence": 0.8100000023841858, "status": "ARGUS_original"}, {"id": 323, "bbox": [[61, 1305], [61, 1302], [75, 1303], [75, 1306]], "text": ":", "confidence": 0.09000000357627869, "status": "ARGUS_original"}, {"id": 324, "bbox": [[62, 1294], [62, 1291], [76, 1292], [76, 1295]], "text": "C", "confidence": 0.9800000190734863, "status": "ARGUS_original"}, {"id": 325, "bbox": [[62, 1287], [62, 1284], [76, 1285], [76, 1288]], "text": "/", "confidence": 0.10999999940395355, "status": "ARGUS_original"}, {"id": 326, "bbox": [[62, 1277], [65, 1237], [80, 1238], [77, 1278]], "text": "Alfonso", "confidence": 0.9399999976158142, "status": "ARGUS_original"}, {"id": 327, "bbox": [[66, 1230], [69, 1189], [84, 1190], [81, 1231]], "text": "G\u00f3mer", "confidence": 0.9599999785423279, "status": "ARGUS_original"}, {"id": 328, "bbox": [[70, 1188], [70, 1185], [84, 1186], [84, 1189]], "text": ".", "confidence": 0.46000000834465027, "status": "ARGUS_original"}, {"id": 329, "bbox": [[70, 1179], [71, 1169], [86, 1170], [85, 1180]], "text": "30", "confidence": 0.8999999761581421, "status": "ARGUS_original"}, {"id": 330, "bbox": [[71, 1165], [71, 1162], [85, 1163], [85, 1166]], "text": "-", "confidence": 0.9200000166893005, "status": "ARGUS_original"}, {"id": 331, "bbox": [[71, 1160], [72, 1147], [87, 1148], [86, 1161]], "text": "32", "confidence": 0.9300000071525574, "status": "ARGUS_original"}, {"id": 332, "bbox": [[72, 1143], [75, 1107], [90, 1108], [87, 1144]], "text": "Madrid", "confidence": 0.9100000262260437, "status": "ARGUS_original"}, {"id": 333, "bbox": [[75, 1105], [75, 1102], [89, 1103], [89, 1106]], "text": ",", "confidence": 0.9800000190734863, "status": "ARGUS_original"}, {"id": 334, "bbox": [[75, 1098], [78, 1059], [93, 1060], [90, 1099]], "text": "Insaita", "confidence": 0.9300000071525574, "status": "ARGUS_original"}, {"id": 335, "bbox": [[79, 1052], [79, 1045], [93, 1046], [93, 1053]], "text": "en", "confidence": 0.9700000286102295, "status": "ARGUS_original"}, {"id": 336, "bbox": [[80, 1036], [80, 1029], [95, 1030], [95, 1037]], "text": "el", "confidence": 0.9900000095367432, "status": "ARGUS_original"}, {"id": 337, "bbox": [[287, 1634], [330, 1633], [331, 1663], [288, 1664]], "text": "CH", "confidence": 0.4699999988079071, "status": "ARGUS_original"}, {"id": 338, "bbox": [[357, 1631], [443, 1628], [444, 1658], [358, 1661]], "text": "HOTEL", "confidence": 0.6600000262260437, "status": "ARGUS_original"}, {"id": 339, "bbox": [[457, 1628], [549, 1625], [550, 1655], [458, 1658]], "text": "GROUP", "confidence": 0.9700000286102295, "status": "ARGUS_original"}, {"id": 340, "bbox": [[574, 1624], [582, 1624], [583, 1653], [575, 1653]], "text": ":", "confidence": 0.10000000149011612, "status": "ARGUS_original"}, {"id": 341, "bbox": [[613, 1623], [645, 1622], [646, 1652], [614, 1653]], "text": "nH", "confidence": 0.5400000214576721, "status": "ARGUS_original"}, {"id": 342, "bbox": [[616, 1647], [646, 1646], [647, 1670], [617, 1671]], "text": "ces", "confidence": 0.23000000417232513, "status": "ARGUS_original"}, {"id": 343, "bbox": [[691, 1645], [708, 1644], [709, 1667], [692, 1668]], "text": "TH", "confidence": 0.25, "status": "ARGUS_original"}, {"id": 344, "bbox": [[715, 1643], [808, 1639], [809, 1663], [716, 1667]], "text": "COLLECTION", "confidence": 0.6700000166893005, "status": "ARGUS_original"}, {"id": 345, "bbox": [[855, 1638], [908, 1636], [909, 1660], [856, 1662]], "text": "nhow", "confidence": 0.8299999833106995, "status": "ARGUS_original"}, {"id": 346, "bbox": [[960, 1634], [1033, 1631], [1034, 1655], [961, 1658]], "text": "Hesperia", "confidence": 0.9599999785423279, "status": "ARGUS_original"}, {"id": 347, "bbox": [[870, 1705], [965, 1704], [965, 1740], [870, 1741]], "text": "Scanned", "confidence": 0.9900000095367432, "status": "ARGUS_original"}, {"id": 348, "bbox": [[981, 1704], [1007, 1704], [1007, 1740], [981, 1740]], "text": "by", "confidence": 0.9900000095367432, "status": "ARGUS_original"}, {"id": 349, "bbox": [[1020, 1704], [1176, 1703], [1176, 1739], [1020, 1740]], "text": "CamScanner", "confidence": 0.9900000095367432, "status": "ARGUS_original"}], "invoice_type": "hotel", "ticket": "20170609_fa463d25-6252-48c9-b75b-59fa1b33df32.pdf", "country": "ES", "tables": []}